<?xml version="1.0" encoding="UTF-8"?>
<office:document-meta xmlns:office="urn:oasis:names:tc:opendocument:xmlns:office:1.0" xmlns:xlink="http://www.w3.org/1999/xlink" xmlns:dc="http://purl.org/dc/elements/1.1/" xmlns:meta="urn:oasis:names:tc:opendocument:xmlns:meta:1.0" xmlns:presentation="urn:oasis:names:tc:opendocument:xmlns:presentation:1.0" xmlns:ooo="http://openoffice.org/2004/office" xmlns:smil="urn:oasis:names:tc:opendocument:xmlns:smil-compatible:1.0" xmlns:anim="urn:oasis:names:tc:opendocument:xmlns:animation:1.0" office:version="1.0"><office:meta><meta:generator>OpenOffice.org/2.3$Linux OpenOffice.org_project/680m5$Build-9221</meta:generator><dc:description>mazu
Author: 李昕迪 / Sin-di Lee
License: CC-BY-NC
Description: This is a view in Cijin, Kaohsiung City, Taiwan.

假日的旗津即使到了冬季還是人山人海。路上行人摩肩擦踵，商家也忙著接待客人，旗津悠閒的形象不復見。即使外面再忙亂，媽祖的天后宮依舊平和的守護著旗津、守護著我們。門前的燈籠海，讓中午的烈日下，也有寧靜的廣場。

投影片背景以GIMP處理為油畫效果。

Website: https://kde-files.org/content/show.php/Mazu?content=110353</dc:description><meta:creation-date>2008-01-24T00:59:00</meta:creation-date><dc:date>2008-01-24T01:08:20</dc:date><meta:editing-cycles>5</meta:editing-cycles><meta:editing-duration>PT9M25S</meta:editing-duration><meta:user-defined meta:name="Info 1"/><meta:user-defined meta:name="Info 2"/><meta:user-defined meta:name="Info 3"/><meta:user-defined meta:name="Info 4"/><meta:document-statistic meta:object-count="44"/></office:meta></office:document-meta>